{"cameraMode":{"drawMode":0,"name":"Shaded","section":"Shading Mode"},"sceneLighting":false,"audioPlay":false,"sceneViewState":{"showFog":true,"showMaterialUpdate":false,"showSkybox":false,"showFlares":true,"showImageEffects":true,"showParticleSystems":true,"showVisualEffectGraphs":true,"m_FxEnabled":true},"in2DMode":false,"pivot":{"x":0.0,"y":2.3999998569488527,"z":0.0},"rotation":{"x":-0.05918749421834946,"y":-0.9297157526016235,"z":0.3203321695327759,"w":-0.17178323864936829},"size":12.12435531616211,"orthographic":false}